sonouno_lhc/__init__.py
sonouno_lhc/__main__.py
sonouno_lhc/bip.wav
sonouno_lhc/io.py
sonouno_lhc/lhc_data.py
sonouno_lhc/lhc_plot.py
sonouno_lhc/lhc_sonification.py
sonouno_lhc/models.py
sonouno_lhc/data/__init__.py
sonouno_lhc/data/sonification_reduced.txt
sonouno_lhc-1.1.1.dist-info/LICENSE
sonouno_lhc-1.1.1.dist-info/METADATA
sonouno_lhc-1.1.1.dist-info/WHEEL
sonouno_lhc-1.1.1.dist-info/top_level.txt
sonouno_lhc-1.1.1.dist-info/RECORD
