Metadata-Version: 2.1
Name: sonouno-lhc
Version: 1.1.1
Summary: Sonification for the HYPATIA experiment at CERN.
Author-email: Johanna Casado <johi.ceh@gmail.com>, Pierre Chanial <pierre.chanial@gmail.com>
Maintainer-email: Pierre Chanial <pierre.chanial@gmail.com>
License: MIT License        
Project-URL: repository, https://github.com/sonoUnoTeam/sonoUno-lhc
Keywords: scientific computing
Classifier: Programming Language :: Python
Classifier: Programming Language :: Python :: 3.10
Classifier: Development Status :: 5 - Production/Stable
Classifier: Intended Audience :: Science/Research
Classifier: Operating System :: OS Independent
Classifier: Topic :: Scientific/Engineering
Requires-Python: >=3.10
License-File: LICENSE
Requires-Dist: matplotlib
Requires-Dist: numpy
Requires-Dist: sonounolib (>=0.5.3)
